{
	code: "worldedit-controls",
	padding: 8,
	disableWorldInteract: false,
	alignment: "LeftFixed",
	rows: [
		{
			height: 30,
			elements: [
				{
					width: 30,
					code: "undo",
					type: "button",
					tooltip: "we-undo-tooltip",
					icon: "undo"
				},
				{
					width: 30,
					code: "redo",
					tooltip: "we-redo-tooltip",
					type: "button",
					icon: "redo"
				},
				{
					"code": "std.settingsRsp",
					"width": 60,
					"height": 30,
					"type": "switch",
					"label": "we-settingsRsp-label",
					"tooltip": "we-settingsRsp-tooltip"
				},
				{
					"code": "std.settingsAxisLock",
					"width": 120,
					"height": 30,
					"label": "we-settingsAxisLock-label",
					"tooltip": "we-settingsAxisLock-tooltip",
					"type": "select",
					"mode": "dropdown",
					"values": ["0", "1", "2", "3", "4"],
					names: ["-", "X", "Y", "Z", "we-settingsAxisLock-h"]
				}
			]
		},
		{
			height: 28,
			elements: [
				{
					code: "std.stepSize",
					width: 120,
					height: 30,
					type: "numberinput",
					label: "we-stepSize-label",
					param: "/we step",
				},
				{
					code: "std.constrain",
					width: 150,
					height: 30,
					"values": ["None", "Selection"],
					names: ["Off", "On"],
					label: "we-constrain-label",
					"tooltip": "we-constrain-tooltip",
					param: "/we constrain",
				}
			]
		}
	]
}
