{
    "code": "diamond",
    "class": "Block",
    "attributes": {
        "handbook": {
            "groupBy": [ "diamond-{stone}-*" ],
        }
    },
    "variantgroups": [
        { "code": "stone", "states": [ "stone" ] },
        { "code": "pattern", "states": [ "clean", "clean-aged", "dark", "dark-aged", "light", "light-aged", "mixed", "mixed-aged" ] }
    ],
    "shape": { "base": "block/basic/cube" },
    "drawtype": "Cube",
    "blockmaterial": "Stone",
    "creativeinventory": {
        "general": [ "*" ],
        "construction": [ "*" ]
    },
    "replaceable": 700,
    "resistance": 4,
    "lightAbsorption": 99,
    "texturesByType": {
        "*": {
            "all": { "base": "game:block/stone/diamond/{pattern}/{stone}*" }
        }
    },
    "sounds": {
        "walk": "walk/stone",
        "place": "block/ceramicplace"
    },
    "heldTpIdleAnimation": "holdbothhandslarge",
    "heldTpUseAnimation": "twohandplaceblock",
    "tpHandTransform": {
        "translation": {
            "x": -1.23,
            "y": -0.91,
            "z": -0.8
        },
        "rotation": {
            "x": -2,
            "y": 25,
            "z": -78
        },
        "scale": 0.4
    }
}