{
	"editor": {
		"collapsedPaths": "Root/origin/body-main/body-back1,Root/origin/balloon3,Root/origin/body-main/body-hood1,Root/origin/body-main/balloon1,Root/origin/body-main/balloon3,Root/origin/body-main/balloon2,Root/origin/body-main/body-mainR/bellows-base4,Root/origin/body-main/body-mainR/pole-sailL1,Root/origin/body-main/tank,Root/origin/balloon2,Root/origin/balloon1,Root/origin/body-main/body-mainR/poleL",
		"allAngles": false,
		"entityTextureMode": false
	},
	"textureWidth": 16,
	"textureHeight": 16,
	"textureSizes": {
	},
	"textures": {
		"charred": "block/wood/charred"
	},
	"elements": [
		{
			"name": "origin",
			"from": [ 8.0, 0.0, 8.0 ],
			"to": [ 8.0, 0.0, 8.0 ],
			"rotationOrigin": [ 8.0, 0.0, 8.0 ],
			"faces": {
			},
			"children": [
				{
					"name": "beam1",
					"from": [ -1.5, -1.0, -1.5 ],
					"to": [ 1.5, 15.0, 1.5 ],
					"rotationOrigin": [ 0.0, -1.0, 0.0 ],
					"rotationX": -15.0,
					"rotationY": 10.0,
					"faces": {
						"north": { "texture": "#charred", "uv": [ 0.0, 4.0, 16.0, 7.0 ], "rotation": 90 },
						"east": { "texture": "#charred", "uv": [ 0.0, 11.0, 16.0, 14.0 ], "rotation": 90 },
						"south": { "texture": "#charred", "uv": [ 0.0, 7.5, 16.0, 10.5 ], "rotation": 90 },
						"west": { "texture": "#charred", "uv": [ 0.0, 7.5, 16.0, 10.5 ], "rotation": 90 },
						"down": { "texture": "#charred", "uv": [ 9.5, 7.5, 12.5, 10.5 ] }
					},
					"children": [
						{
							"name": "beam2",
							"from": [ 0.0, 15.8, 0.0 ],
							"to": [ 3.0, 31.8, 3.0 ],
							"rotationOrigin": [ 1.5, 15.8, 1.5 ],
							"rotationX": -5.0,
							"rotationZ": 2.0,
							"faces": {
								"north": { "texture": "#charred", "uv": [ 0.0, 9.5, 16.0, 12.5 ], "rotation": 90 },
								"east": { "texture": "#charred", "uv": [ 0.0, 2.0, 16.0, 5.0 ], "rotation": 90 },
								"south": { "texture": "#charred", "uv": [ 0.0, 6.5, 16.0, 9.5 ], "rotation": 90 },
								"west": { "texture": "#charred", "uv": [ 0.0, 11.0, 16.0, 14.0 ], "rotation": 90 },
								"up": { "texture": "#charred", "uv": [ 2.0, 8.5, 5.0, 11.5 ] }
							},
							"children": [
								{
									"name": "chunk1",
									"from": [ 0.0, 16.0, 0.0 ],
									"to": [ 1.0, 20.0, 1.0 ],
									"rotationOrigin": [ 0.0, 16.0, 0.0 ],
									"faces": {
										"north": { "texture": "#charred", "uv": [ 0.5, 3.0, 4.5, 4.0 ], "rotation": 90 },
										"east": { "texture": "#charred", "uv": [ 6.0, 12.0, 10.0, 13.0 ], "rotation": 90 },
										"south": { "texture": "#charred", "uv": [ 6.5, 10.5, 10.5, 11.5 ], "rotation": 90 },
										"west": { "texture": "#charred", "uv": [ 3.5, 3.5, 7.5, 4.5 ], "rotation": 90 },
										"up": { "texture": "#charred", "uv": [ 7.5, 8.0, 8.5, 9.0 ] }
									}
								},
								{
									"name": "chunk2",
									"from": [ 1.0, 16.0, 1.0 ],
									"to": [ 2.0, 18.0, 2.0 ],
									"rotationOrigin": [ 1.0, 16.0, 1.0 ],
									"faces": {
										"north": { "texture": "#charred", "uv": [ 11.0, 7.0, 13.0, 8.0 ], "rotation": 90 },
										"east": { "texture": "#charred", "uv": [ 3.0, 13.5, 5.0, 14.5 ], "rotation": 90 },
										"south": { "texture": "#charred", "uv": [ 5.5, 2.0, 7.5, 3.0 ], "rotation": 90 },
										"west": { "texture": "#charred", "uv": [ 11.0, 8.0, 13.0, 9.0 ], "rotation": 90 },
										"up": { "texture": "#charred", "uv": [ 7.5, 7.5, 8.5, 8.5 ] }
									}
								},
								{
									"name": "chunk3",
									"from": [ 2.0, 16.0, 2.0 ],
									"to": [ 3.0, 22.0, 3.0 ],
									"rotationOrigin": [ 2.0, 16.0, 2.0 ],
									"faces": {
										"north": { "texture": "#charred", "uv": [ 4.0, 2.5, 10.0, 3.5 ], "rotation": 90 },
										"east": { "texture": "#charred", "uv": [ 8.0, 8.5, 14.0, 9.5 ], "rotation": 90 },
										"south": { "texture": "#charred", "uv": [ 1.5, 7.5, 7.5, 8.5 ], "rotation": 90 },
										"west": { "texture": "#charred", "uv": [ 3.5, 10.5, 9.5, 11.5 ], "rotation": 90 },
										"up": { "texture": "#charred", "uv": [ 6.5, 12.0, 7.5, 13.0 ] }
									}
								},
								{
									"name": "chunk4",
									"from": [ 0.0, 16.0, 1.0 ],
									"to": [ 2.0, 17.0, 3.0 ],
									"rotationOrigin": [ 1.0, 16.0, 2.0 ],
									"faces": {
										"south": { "texture": "#charred", "uv": [ 9.0, 7.5, 10.0, 9.5 ], "rotation": 90 },
										"west": { "texture": "#charred", "uv": [ 5.0, 9.5, 6.0, 11.5 ], "rotation": 90 },
										"up": { "texture": "#charred", "uv": [ 4.5, 4.5, 6.5, 6.5 ] }
									}
								},
								{
									"name": "chunk5",
									"from": [ 2.0, 16.0, 0.0 ],
									"to": [ 3.0, 17.0, 1.0 ],
									"rotationOrigin": [ 2.0, 16.0, 0.0 ],
									"faces": {
										"north": { "texture": "#charred", "uv": [ 0.5, 9.5, 1.5, 10.5 ], "rotation": 90 },
										"east": { "texture": "#charred", "uv": [ 4.5, 5.5, 5.5, 6.5 ], "rotation": 90 },
										"south": { "texture": "#charred", "uv": [ 10.0, 14.5, 11.0, 15.5 ], "rotation": 90 },
										"west": { "texture": "#charred", "uv": [ 7.5, 2.5, 8.5, 3.5 ], "rotation": 90 },
										"up": { "texture": "#charred", "uv": [ 6.5, 10.0, 7.5, 11.0 ] }
									}
								},
								{
									"name": "chunk6",
									"from": [ 0.0, 17.0, 2.0 ],
									"to": [ 1.0, 19.0, 3.0 ],
									"rotationOrigin": [ 0.0, 17.0, 2.0 ],
									"faces": {
										"north": { "texture": "#charred", "uv": [ 7.5, 0.5, 9.5, 1.5 ], "rotation": 90 },
										"east": { "texture": "#charred", "uv": [ 3.0, 8.0, 5.0, 9.0 ], "rotation": 90 },
										"south": { "texture": "#charred", "uv": [ 2.5, 5.0, 4.5, 6.0 ], "rotation": 90 },
										"west": { "texture": "#charred", "uv": [ 4.0, 10.0, 6.0, 11.0 ], "rotation": 90 },
										"up": { "texture": "#charred", "uv": [ 7.5, 3.0, 8.5, 4.0 ] }
									}
								}
							]
						}
					]
				},
				{
					"name": "beam3",
					"from": [ 3.0, -0.2, 1.0 ],
					"to": [ 5.0, 15.8, 3.0 ],
					"rotationOrigin": [ 4.0, -0.2, 2.0 ],
					"rotationX": 5.0,
					"rotationY": -22.5,
					"faces": {
						"north": { "texture": "#charred", "uv": [ 0.0, 6.5, 16.0, 8.5 ], "rotation": 90 },
						"east": { "texture": "#charred", "uv": [ 0.0, 9.5, 16.0, 11.5 ], "rotation": 90 },
						"south": { "texture": "#charred", "uv": [ 0.0, 1.5, 16.0, 3.5 ], "rotation": 90 },
						"west": { "texture": "#charred", "uv": [ 0.0, 12.0, 16.0, 14.0 ], "rotation": 90 },
						"up": { "texture": "#charred", "uv": [ 13.0, 0.5, 15.0, 2.5 ] },
						"down": { "texture": "#charred", "uv": [ 10.0, 6.0, 12.0, 8.0 ] }
					},
					"children": [
						{
							"name": "chunk7",
							"from": [ 0.0, 16.0, 0.0 ],
							"to": [ 1.0, 24.0, 1.0 ],
							"rotationOrigin": [ 0.0, 16.0, 0.0 ],
							"faces": {
								"north": { "texture": "#charred", "uv": [ 3.0, 1.0, 11.0, 2.0 ], "rotation": 90 },
								"east": { "texture": "#charred", "uv": [ 5.0, 6.5, 13.0, 7.5 ], "rotation": 90 },
								"south": { "texture": "#charred", "uv": [ 6.5, 8.5, 14.5, 9.5 ], "rotation": 90 },
								"west": { "texture": "#charred", "uv": [ 7.5, 11.5, 15.5, 12.5 ], "rotation": 90 },
								"up": { "texture": "#charred", "uv": [ 9.0, 6.0, 10.0, 7.0 ] }
							}
						},
						{
							"name": "chunk8",
							"from": [ 1.0, 16.0, 1.0 ],
							"to": [ 2.0, 20.0, 2.0 ],
							"rotationOrigin": [ 1.0, 16.0, 1.0 ],
							"faces": {
								"north": { "texture": "#charred", "uv": [ 8.5, 5.5, 12.5, 6.5 ], "rotation": 90 },
								"east": { "texture": "#charred", "uv": [ 5.0, 11.5, 9.0, 12.5 ], "rotation": 90 },
								"south": { "texture": "#charred", "uv": [ 0.5, 11.5, 4.5, 12.5 ], "rotation": 90 },
								"west": { "texture": "#charred", "uv": [ 6.5, 13.5, 10.5, 14.5 ], "rotation": 90 },
								"up": { "texture": "#charred", "uv": [ 4.0, 12.0, 5.0, 13.0 ] }
							}
						},
						{
							"name": "chunk9",
							"from": [ 0.0, 16.0, 1.0 ],
							"to": [ 1.0, 18.0, 2.0 ],
							"rotationOrigin": [ 0.0, 16.0, 1.0 ],
							"faces": {
								"north": { "texture": "#charred", "uv": [ 10.0, 11.0, 12.0, 12.0 ], "rotation": 90 },
								"east": { "texture": "#charred", "uv": [ 11.0, 0.5, 13.0, 1.5 ], "rotation": 90 },
								"south": { "texture": "#charred", "uv": [ 8.0, 14.0, 10.0, 15.0 ], "rotation": 90 },
								"west": { "texture": "#charred", "uv": [ 1.5, 9.5, 3.5, 10.5 ], "rotation": 90 },
								"up": { "texture": "#charred", "uv": [ 3.0, 4.0, 4.0, 5.0 ] }
							}
						}
					]
				},
				{
					"name": "beam4",
					"from": [ -2.0, -0.4, 4.0 ],
					"to": [ 0.0, 15.6, 6.0 ],
					"rotationOrigin": [ -1.0, -0.4, 5.0 ],
					"rotationX": -10.0,
					"rotationZ": 5.0,
					"faces": {
						"north": { "texture": "#charred", "uv": [ 0.0, 6.5, 16.0, 8.5 ], "rotation": 90 },
						"east": { "texture": "#charred", "uv": [ 0.0, 9.5, 16.0, 11.5 ], "rotation": 90 },
						"south": { "texture": "#charred", "uv": [ 0.0, 1.5, 16.0, 3.5 ], "rotation": 90 },
						"west": { "texture": "#charred", "uv": [ 0.0, 12.0, 16.0, 14.0 ], "rotation": 90 },
						"down": { "texture": "#charred", "uv": [ 10.0, 6.0, 12.0, 8.0 ] }
					},
					"children": [
						{
							"name": "beam5",
							"from": [ 0.0, 16.0, 0.0 ],
							"to": [ 2.0, 26.0, 2.0 ],
							"rotationOrigin": [ 1.0, 16.0, 1.0 ],
							"faces": {
								"north": { "texture": "#charred", "uv": [ 0.0, 0.0, 10.0, 2.0 ], "rotation": 90 },
								"east": { "texture": "#charred", "uv": [ 0.0, 0.0, 10.0, 2.0 ], "rotation": 90 },
								"south": { "texture": "#charred", "uv": [ 0.0, 0.0, 10.0, 2.0 ], "rotation": 90 },
								"west": { "texture": "#charred", "uv": [ 0.0, 0.0, 10.0, 2.0 ], "rotation": 90 },
								"up": { "texture": "#charred", "uv": [ 0.0, 0.0, 2.0, 2.0 ] }
							},
							"children": [
								{
									"name": "chunk10",
									"from": [ 0.0, 10.0, 0.0 ],
									"to": [ 1.0, 13.0, 1.0 ],
									"rotationOrigin": [ 0.0, 10.0, 0.0 ],
									"faces": {
										"north": { "texture": "#charred", "uv": [ 0.0, 0.0, 3.0, 1.0 ], "rotation": 90 },
										"east": { "texture": "#charred", "uv": [ 0.0, 0.0, 3.0, 1.0 ], "rotation": 90 },
										"south": { "texture": "#charred", "uv": [ 0.0, 0.0, 3.0, 1.0 ], "rotation": 90 },
										"west": { "texture": "#charred", "uv": [ 0.0, 0.0, 3.0, 1.0 ], "rotation": 90 },
										"up": { "texture": "#charred", "uv": [ 0.0, 0.0, 1.0, 1.0 ] }
									}
								},
								{
									"name": "chunk11",
									"from": [ 1.0, 10.0, 1.0 ],
									"to": [ 2.0, 12.0, 2.0 ],
									"rotationOrigin": [ 1.0, 10.0, 1.0 ],
									"faces": {
										"north": { "texture": "#charred", "uv": [ 0.0, 0.0, 2.0, 1.0 ], "rotation": 90 },
										"east": { "texture": "#charred", "uv": [ 0.0, 0.0, 2.0, 1.0 ], "rotation": 90 },
										"south": { "texture": "#charred", "uv": [ 0.0, 0.0, 2.0, 1.0 ], "rotation": 90 },
										"west": { "texture": "#charred", "uv": [ 0.0, 0.0, 2.0, 1.0 ], "rotation": 90 },
										"up": { "texture": "#charred", "uv": [ 0.0, 0.0, 1.0, 1.0 ] }
									}
								},
								{
									"name": "chunk12",
									"from": [ 0.5, 10.0, 1.0 ],
									"to": [ 1.0, 16.0, 1.5 ],
									"rotationOrigin": [ 1.0, 10.0, 1.0 ],
									"faces": {
										"north": { "texture": "#charred", "uv": [ 0.0, 0.0, 6.0, 0.5 ], "rotation": 90 },
										"east": { "texture": "#charred", "uv": [ 0.0, 0.0, 6.0, 0.5 ], "rotation": 90 },
										"south": { "texture": "#charred", "uv": [ 0.0, 0.0, 6.0, 0.5 ], "rotation": 90 },
										"west": { "texture": "#charred", "uv": [ 0.0, 0.0, 6.0, 0.5 ], "rotation": 90 },
										"up": { "texture": "#charred", "uv": [ 0.0, 0.0, 0.5, 0.5 ] }
									}
								}
							]
						}
					]
				},
				{
					"name": "beam6",
					"from": [ -5.5, -1.0, 0.5 ],
					"to": [ -2.5, 15.0, 3.5 ],
					"rotationOrigin": [ -4.0, -1.0, 2.0 ],
					"rotationY": 22.5,
					"rotationZ": -22.5,
					"faces": {
						"north": { "texture": "#charred", "uv": [ 0.0, 8.0, 16.0, 11.0 ], "rotation": 90 },
						"east": { "texture": "#charred", "uv": [ 0.0, 6.5, 16.0, 9.5 ], "rotation": 90 },
						"south": { "texture": "#charred", "uv": [ 0.0, 5.0, 16.0, 8.0 ], "rotation": 90 },
						"west": { "texture": "#charred", "uv": [ 0.0, 1.0, 16.0, 4.0 ], "rotation": 90 },
						"down": { "texture": "#charred", "uv": [ 0.0, 11.5, 3.0, 14.5 ] }
					},
					"children": [
						{
							"name": "beam7",
							"from": [ 0.0, 15.8, 0.0 ],
							"to": [ 3.0, 26.8, 3.0 ],
							"rotationOrigin": [ 1.5, 15.8, 1.5 ],
							"rotationX": 1.0,
							"rotationZ": 4.0,
							"faces": {
								"north": { "texture": "#charred", "uv": [ 1.0, 1.0, 12.0, 4.0 ], "rotation": 90 },
								"east": { "texture": "#charred", "uv": [ 1.5, 12.5, 12.5, 15.5 ], "rotation": 90 },
								"south": { "texture": "#charred", "uv": [ 3.5, 10.0, 14.5, 13.0 ], "rotation": 90 },
								"west": { "texture": "#charred", "uv": [ 3.0, 12.5, 14.0, 15.5 ], "rotation": 90 },
								"up": { "texture": "#charred", "uv": [ 10.5, 12.0, 13.5, 15.0 ] }
							},
							"children": [
								{
									"name": "chunk13",
									"from": [ 0.0, 11.0, 0.0 ],
									"to": [ 1.0, 13.0, 1.0 ],
									"rotationOrigin": [ 0.0, 11.0, 0.0 ],
									"faces": {
										"north": { "texture": "#charred", "uv": [ 11.0, 10.5, 13.0, 11.5 ], "rotation": 90 },
										"east": { "texture": "#charred", "uv": [ 9.5, 7.0, 11.5, 8.0 ], "rotation": 90 },
										"south": { "texture": "#charred", "uv": [ 0.0, 8.0, 2.0, 9.0 ], "rotation": 90 },
										"west": { "texture": "#charred", "uv": [ 10.5, 13.0, 12.5, 14.0 ], "rotation": 90 },
										"up": { "texture": "#charred", "uv": [ 1.0, 5.0, 2.0, 6.0 ] }
									}
								},
								{
									"name": "chunk14",
									"from": [ 1.0, 11.0, 1.0 ],
									"to": [ 2.0, 17.0, 2.0 ],
									"rotationOrigin": [ 1.0, 11.0, 1.0 ],
									"faces": {
										"north": { "texture": "#charred", "uv": [ 4.5, 9.5, 10.5, 10.5 ], "rotation": 90 },
										"east": { "texture": "#charred", "uv": [ 3.5, 3.0, 9.5, 4.0 ], "rotation": 90 },
										"south": { "texture": "#charred", "uv": [ 8.5, 5.0, 14.5, 6.0 ], "rotation": 90 },
										"west": { "texture": "#charred", "uv": [ 6.5, 8.0, 12.5, 9.0 ], "rotation": 90 },
										"up": { "texture": "#charred", "uv": [ 11.5, 2.0, 12.5, 3.0 ] }
									}
								},
								{
									"name": "chunk15",
									"from": [ 2.0, 11.0, 2.0 ],
									"to": [ 3.0, 14.0, 3.0 ],
									"rotationOrigin": [ 2.0, 11.0, 2.0 ],
									"faces": {
										"north": { "texture": "#charred", "uv": [ 5.0, 13.5, 8.0, 14.5 ], "rotation": 90 },
										"east": { "texture": "#charred", "uv": [ 2.5, 14.0, 5.5, 15.0 ], "rotation": 90 },
										"south": { "texture": "#charred", "uv": [ 11.5, 3.5, 14.5, 4.5 ], "rotation": 90 },
										"west": { "texture": "#charred", "uv": [ 6.0, 12.5, 9.0, 13.5 ], "rotation": 90 },
										"up": { "texture": "#charred", "uv": [ 13.5, 10.5, 14.5, 11.5 ] }
									}
								},
								{
									"name": "chunk16",
									"from": [ 0.0, 11.0, 1.0 ],
									"to": [ 2.0, 12.0, 3.0 ],
									"rotationOrigin": [ 1.0, 11.0, 2.0 ],
									"faces": {
										"south": { "texture": "#charred", "uv": [ 10.0, 11.0, 11.0, 13.0 ], "rotation": 90 },
										"west": { "texture": "#charred", "uv": [ 2.0, 12.5, 3.0, 14.5 ], "rotation": 90 },
										"up": { "texture": "#charred", "uv": [ 2.5, 11.5, 4.5, 13.5 ] }
									}
								},
								{
									"name": "chunk17",
									"from": [ 2.0, 11.0, 0.0 ],
									"to": [ 3.0, 12.0, 1.0 ],
									"rotationOrigin": [ 2.0, 11.0, 0.0 ],
									"faces": {
										"north": { "texture": "#charred", "uv": [ 4.0, 4.5, 5.0, 5.5 ], "rotation": 90 },
										"east": { "texture": "#charred", "uv": [ 7.0, 5.5, 8.0, 6.5 ], "rotation": 90 },
										"south": { "texture": "#charred", "uv": [ 9.5, 10.5, 10.5, 11.5 ], "rotation": 90 },
										"west": { "texture": "#charred", "uv": [ 12.0, 14.0, 13.0, 15.0 ], "rotation": 90 },
										"up": { "texture": "#charred", "uv": [ 8.0, 12.5, 9.0, 13.5 ] }
									}
								},
								{
									"name": "chunk18",
									"from": [ 0.0, 12.0, 2.0 ],
									"to": [ 1.0, 16.0, 3.0 ],
									"rotationOrigin": [ 0.0, 12.0, 2.0 ],
									"faces": {
										"north": { "texture": "#charred", "uv": [ 8.0, 1.0, 12.0, 2.0 ], "rotation": 90 },
										"east": { "texture": "#charred", "uv": [ 0.0, 3.0, 4.0, 4.0 ], "rotation": 90 },
										"south": { "texture": "#charred", "uv": [ 3.0, 11.5, 7.0, 12.5 ], "rotation": 90 },
										"west": { "texture": "#charred", "uv": [ 11.0, 11.0, 15.0, 12.0 ], "rotation": 90 },
										"up": { "texture": "#charred", "uv": [ 2.0, 14.0, 3.0, 15.0 ] }
									}
								}
							]
						}
					]
				},
				{
					"name": "beam8",
					"from": [ -3.0, -0.2, -5.0 ],
					"to": [ -1.0, 11.8, -3.0 ],
					"rotationOrigin": [ -2.0, -0.2, -4.0 ],
					"rotationX": 22.5,
					"rotationY": -22.5,
					"rotationZ": 22.5,
					"faces": {
						"north": { "texture": "#charred", "uv": [ 1.5, 1.5, 13.5, 3.5 ], "rotation": 90 },
						"east": { "texture": "#charred", "uv": [ 0.0, 5.5, 12.0, 7.5 ], "rotation": 90 },
						"south": { "texture": "#charred", "uv": [ 0.5, 6.0, 12.5, 8.0 ], "rotation": 90 },
						"west": { "texture": "#charred", "uv": [ 3.0, 5.0, 15.0, 7.0 ], "rotation": 90 },
						"up": { "texture": "#charred", "uv": [ 5.5, 1.0, 7.5, 3.0 ] },
						"down": { "texture": "#charred", "uv": [ 5.0, 8.5, 7.0, 10.5 ] }
					},
					"children": [
						{
							"name": "chunk19",
							"from": [ 0.0, 12.0, 0.0 ],
							"to": [ 1.0, 20.0, 1.0 ],
							"rotationOrigin": [ 0.0, 12.0, 0.0 ],
							"faces": {
								"north": { "texture": "#charred", "uv": [ 6.0, 8.5, 14.0, 9.5 ], "rotation": 90 },
								"east": { "texture": "#charred", "uv": [ 1.0, 5.5, 9.0, 6.5 ], "rotation": 90 },
								"south": { "texture": "#charred", "uv": [ 0.0, 9.5, 8.0, 10.5 ], "rotation": 90 },
								"west": { "texture": "#charred", "uv": [ 1.5, 12.0, 9.5, 13.0 ], "rotation": 90 },
								"up": { "texture": "#charred", "uv": [ 10.5, 10.0, 11.5, 11.0 ] }
							}
						},
						{
							"name": "chunk20",
							"from": [ 1.0, 12.0, 1.0 ],
							"to": [ 2.0, 17.0, 2.0 ],
							"rotationOrigin": [ 1.0, 12.0, 1.0 ],
							"faces": {
								"north": { "texture": "#charred", "uv": [ 2.5, 8.5, 7.5, 9.5 ], "rotation": 90 },
								"east": { "texture": "#charred", "uv": [ 7.5, 9.5, 12.5, 10.5 ], "rotation": 90 },
								"south": { "texture": "#charred", "uv": [ 10.0, 4.5, 15.0, 5.5 ], "rotation": 90 },
								"west": { "texture": "#charred", "uv": [ 8.0, 7.0, 13.0, 8.0 ], "rotation": 90 },
								"up": { "texture": "#charred", "uv": [ 12.0, 13.5, 13.0, 14.5 ] }
							}
						},
						{
							"name": "chunk21",
							"from": [ 0.0, 12.0, 1.0 ],
							"to": [ 1.0, 14.0, 2.0 ],
							"rotationOrigin": [ 0.0, 12.0, 1.0 ],
							"faces": {
								"north": { "texture": "#charred", "uv": [ 4.5, 3.5, 6.5, 4.5 ], "rotation": 90 },
								"east": { "texture": "#charred", "uv": [ 8.0, 8.0, 10.0, 9.0 ], "rotation": 90 },
								"south": { "texture": "#charred", "uv": [ 6.0, 0.0, 8.0, 1.0 ], "rotation": 90 },
								"west": { "texture": "#charred", "uv": [ 0.0, 14.0, 2.0, 15.0 ], "rotation": 90 },
								"up": { "texture": "#charred", "uv": [ 11.5, 13.5, 12.5, 14.5 ] }
							}
						}
					]
				}
			]
		}
	]}