{
	"editor": {
		"backDropShape": "entity/humanoid/villager-child",
		"allAngles": false,
		"entityTextureMode": false
	},
	"textureWidth": 16,
	"textureHeight": 16,
	"textureSizes": {
	},
	"textures": {
		"black": "block/cloth/linen/black",
		"blue": "block/cloth/linen/blue",
		"plainoak": "block/wood/plainoak"
	},
	"elements": [
		{
			"name": "stick",
			"stepParentName": "HandL",
			"from": [ -1.0, -12.5, -0.5 ],
			"to": [ 0.0, 3.5, 0.5 ],
			"rotationOrigin": [ -1.0, -0.5, 0.0 ],
			"rotationZ": 90.0,
			"faces": {
				"north": { "texture": "#plainoak", "uv": [ 0.0, 1.0, 16.0, 2.0 ], "rotation": 90 },
				"east": { "texture": "#plainoak", "uv": [ 0.0, 6.5, 16.0, 7.5 ], "rotation": 90 },
				"south": { "texture": "#plainoak", "uv": [ 0.0, 10.5, 16.0, 11.5 ], "rotation": 90 },
				"west": { "texture": "#plainoak", "uv": [ 0.0, 6.5, 16.0, 7.5 ], "rotation": 90, "windMode": [-1,-1,-1,-1], "windData": [0,0,1,1] },
				"down": { "texture": "#plainoak", "uv": [ 11.5, 14.0, 12.5, 15.0 ] }
			},
			"children": [
				{
					"name": "head",
					"from": [ -1.0, 16.0, -1.0 ],
					"to": [ 2.0, 22.0, 2.0 ],
					"rotationOrigin": [ -1.0, 17.5, 0.5 ],
					"faces": {
						"north": { "texture": "#blue", "uv": [ 8.5, 0.0, 11.5, 6.0 ] },
						"east": { "texture": "#blue", "uv": [ 10.0, 6.5, 13.0, 12.5 ] },
						"south": { "texture": "#blue", "uv": [ 2.5, 5.0, 5.5, 11.0 ] },
						"west": { "texture": "#blue", "uv": [ 3.0, 7.5, 6.0, 13.5 ] },
						"up": { "texture": "#blue", "uv": [ 8.0, 4.5, 11.0, 7.5 ] },
						"down": { "texture": "#blue", "uv": [ 7.0, 4.5, 10.0, 7.5 ] }
					},
					"children": [
						{
							"name": "ear2",
							"from": [ 1.5, 6.0, 0.0 ],
							"to": [ 2.5, 9.0, 1.0 ],
							"rotationOrigin": [ 2.5, 6.0, 1.0 ],
							"rotationX": -20.0,
							"faces": {
								"north": { "texture": "#blue", "uv": [ 2.0, 2.5, 3.0, 5.5 ] },
								"east": { "texture": "#blue", "uv": [ 11.5, 3.5, 12.5, 6.5 ] },
								"south": { "texture": "#blue", "uv": [ 2.5, 3.5, 3.5, 6.5 ] },
								"west": { "texture": "#blue", "uv": [ 7.0, 12.0, 8.0, 15.0 ] },
								"up": { "texture": "#blue", "uv": [ 1.0, 3.0, 2.0, 4.0 ] },
								"down": { "texture": "#blue", "uv": [ 7.0, 2.5, 8.0, 3.5 ] }
							}
						},
						{
							"name": "nose",
							"from": [ -3.0, 3.0, 0.5 ],
							"to": [ 0.0, 5.0, 2.5 ],
							"rotationOrigin": [ -2.0, 4.0, 0.5 ],
							"faces": {
								"north": { "texture": "#blue", "uv": [ 8.5, 12.5, 11.5, 14.5 ], "windMode": [-1,-1,-1,-1] },
								"south": { "texture": "#blue", "uv": [ 9.0, 9.0, 12.0, 11.0 ] },
								"west": { "texture": "#blue", "uv": [ 1.0, 7.0, 3.0, 9.0 ] },
								"up": { "texture": "#blue", "uv": [ 9.0, 1.0, 12.0, 3.0 ], "windMode": [-1,-1,-1,-1] },
								"down": { "texture": "#blue", "uv": [ 11.0, 3.0, 14.0, 5.0 ] }
							},
							"children": [
								{
									"name": "Nostril1",
									"from": [ -0.02, 1.0, 1.5 ],
									"to": [ 0.98, 1.5, 2.02 ],
									"rotationOrigin": [ 0.0, 1.0, 1.5 ],
									"faces": {
										"north": { "texture": "#black", "uv": [ 2.5, 2.5, 3.5, 3.0 ] },
										"east": { "texture": "#black", "uv": [ 6.5, 13.5, 7.0, 14.0 ] },
										"south": { "texture": "#black", "uv": [ 7.5, 6.0, 8.5, 6.5 ] },
										"west": { "texture": "#black", "uv": [ 1.5, 1.5, 2.0, 2.0 ] },
										"up": { "texture": "#black", "uv": [ 14.5, 15.0, 15.5, 15.5 ] },
										"down": { "texture": "#black", "uv": [ 8.0, 0.5, 9.0, 1.0 ] }
									}
								},
								{
									"name": "Nostril2",
									"from": [ -0.02, 1.0, -0.02 ],
									"to": [ 0.98, 1.5, 0.5 ],
									"rotationOrigin": [ 0.0, 1.0, 0.0 ],
									"faces": {
										"north": { "texture": "#black", "uv": [ 0.0, 0.5, 1.0, 1.0 ] },
										"east": { "texture": "#black", "uv": [ 0.0, 0.0, 0.5, 0.5 ] },
										"south": { "texture": "#black", "uv": [ 0.0, 0.0, 1.0, 0.5 ] },
										"west": { "texture": "#black", "uv": [ 0.5, 0.0, 1.0, 0.5 ] },
										"up": { "texture": "#black", "uv": [ 0.0, 0.0, 1.0, 0.5 ] },
										"down": { "texture": "#black", "uv": [ 0.5, 0.0, 1.5, 0.5 ] }
									}
								}
							]
						},
						{
							"name": "ear3",
							"from": [ 1.5, 6.0, 2.0 ],
							"to": [ 2.5, 9.0, 3.0 ],
							"rotationOrigin": [ 2.5, 6.0, 2.0 ],
							"rotationX": 20.0,
							"faces": {
								"north": { "texture": "#blue", "uv": [ 2.0, 2.5, 3.0, 5.5 ] },
								"east": { "texture": "#blue", "uv": [ 11.5, 3.5, 12.5, 6.5 ] },
								"south": { "texture": "#blue", "uv": [ 2.5, 3.5, 3.5, 6.5 ] },
								"west": { "texture": "#blue", "uv": [ 7.0, 12.0, 8.0, 15.0 ] },
								"up": { "texture": "#blue", "uv": [ 1.0, 3.0, 2.0, 4.0 ] },
								"down": { "texture": "#blue", "uv": [ 7.0, 2.5, 8.0, 3.5 ] }
							}
						},
						{
							"name": "EyeL",
							"from": [ -0.02, 5.0, 2.5 ],
							"to": [ 0.48, 5.5, 3.02 ],
							"rotationOrigin": [ 0.0, 5.0, 2.5 ],
							"faces": {
								"north": { "texture": "#black", "uv": [ 2.5, 2.5, 3.0, 3.0 ] },
								"east": { "texture": "#black", "uv": [ 6.5, 13.5, 7.0, 14.0 ] },
								"south": { "texture": "#black", "uv": [ 7.5, 6.0, 8.0, 6.5 ] },
								"west": { "texture": "#black", "uv": [ 1.5, 1.5, 2.0, 2.0 ] },
								"up": { "texture": "#black", "uv": [ 14.5, 15.0, 15.0, 15.5 ] },
								"down": { "texture": "#black", "uv": [ 8.0, 0.5, 8.5, 1.0 ] }
							}
						},
						{
							"name": "EyeL2",
							"from": [ -0.02, 5.0, -0.02 ],
							"to": [ 0.48, 5.5, 0.5 ],
							"rotationOrigin": [ 0.0, 5.0, -0.02 ],
							"faces": {
								"north": { "texture": "#black", "uv": [ 2.5, 2.5, 3.0, 3.0 ] },
								"east": { "texture": "#black", "uv": [ 6.5, 13.5, 7.0, 14.0 ] },
								"south": { "texture": "#black", "uv": [ 7.5, 6.0, 8.0, 6.5 ] },
								"west": { "texture": "#black", "uv": [ 2.0, 2.0, 2.5, 2.5 ] },
								"up": { "texture": "#black", "uv": [ 14.5, 15.0, 15.0, 15.5 ] },
								"down": { "texture": "#black", "uv": [ 8.0, 0.5, 8.5, 1.0 ] }
							}
						}
					]
				}
			]
		}
	]}